Workbook

Sheet 目次
B1: Excel グラフ作成 演習問題
B2: 各「問題」シートのデータから自分でグラフを作成し、「解答」シートと見比べてください。
B4: No. | C4: グラフの種類 | D4: テーマ | E4: 難易度 | F4: 完了
B5: 問題1 | C5: 集合縦棒グラフ | D5: 支店別の売上を比較する | E5: ★ | F5: =IF(COUNTIF(問題1!C:C,"○")>0,COUNTIF(問題1!C:C,"○")&"項目","")
B6: 問題2 | C6: 折れ線グラフ | D6: 月別売上の推移を見る(2系列) | E6: ★ | F6: =IF(COUNTIF(問題2!C:C,"○")>0,COUNTIF(問題2!C:C,"○")&"項目","")
B7: 問題3 | C7: 円グラフ | D7: 経費の構成比を示す | E7: ★ | F7: =IF(COUNTIF(問題3!C:C,"○")>0,COUNTIF(問題3!C:C,"○")&"項目","")
B8: 問題4 | C8: 積み上げ縦棒グラフ | D8: 四半期ごとの製品別内訳 | E8: ★★ | F8: =IF(COUNTIF(問題4!C:C,"○")>0,COUNTIF(問題4!C:C,"○")&"項目","")
B9: 問題5 | C9: 横棒グラフ(並べ替え) | D9: 商品売上ランキングを見やすく | E9: ★★ | F9: =IF(COUNTIF(問題5!C:C,"○")>0,COUNTIF(問題5!C:C,"○")&"項目","")
B10: 問題6 | C10: 複合グラフ(第2軸) | D10: 売上(棒)と利益率(折れ線)を1つに | E10: ★★★ | F10: =IF(COUNTIF(問題6!C:C,"○")>0,COUNTIF(問題6!C:C,"○")&"項目","")
B11: 問題7 | C11: 散布図+近似曲線 | D11: 広告費と売上の関係を分析 | E11: ★★★ | F11: =IF(COUNTIF(問題7!C:C,"○")>0,COUNTIF(問題7!C:C,"○")&"項目","")
B13: 【使い方】
B14: 1. 各「問題」シートの問題文を読み、表のデータを使ってグラフを作成します(グラフはデータの右側に配置)。
B15: 2. 困ったら【ヒント】の操作手順を参照してください。
B16: 3. 作成後、【セルフチェック】の各項目を確認し、黄色セルに ○ を入力します(目次の「完了」欄に反映)。
B17: 4. 「解答」シートに完成例があります。見た目の細部(色など)は一致しなくてOKです。
B18: ※ 青字の数値は入力データです。値を変えるとグラフが連動することも確認してみましょう。
B19: ※ ヒントは Mac 版 Excel の操作です。グラフを選ぶと上部に[グラフのデザイン]タブと[書式]タブが現れます。
B20: ※ 右クリック = control+クリック、またはトラックパッドの2本指クリック。
B21: ※ 軸ラベル・データラベル・凡例・近似曲線などは、すべて [グラフのデザイン] → [グラフ要素を追加] から付けられます。

Sheet 問題1
B1: 問題1 集合縦棒グラフ
B2: 難易度 ★
B4: 支店 | C4: 売上(千円)
B5: 札幌 | C5: 4200
B6: 仙台 | C6: 3100
B7: 東京 | C7: 8600
B8: 名古屋 | C8: 5400
B9: 大阪 | C9: 7300
B10: 福岡 | C10: 3900
B11: 合計 | C11: =SUM(C5:C10) -> 32500
B13: 【問題】
B14: B4:C10 のデータ(合計行は含めない)から「集合縦棒グラフ」を作成しなさい。
B15: ・グラフタイトル:「支店別売上」
B16: ・縦軸ラベル:「売上(千円)」、横軸ラベル:「支店」
B17: ・凡例は非表示、各棒の上にデータラベル(値)を表示
B19: 【ヒント(操作手順)】
B20: B4:C10 を選択 → [挿入]タブ → 縦棒グラフのアイコン → [集合縦棒]
B21: グラフの余白をクリックして選択 → [グラフのデザイン]タブ → 左端の[グラフ要素を追加]
B22: ・[軸ラベル] → [第1横軸]、もう一度 [軸ラベル] → [第1縦軸]
B23: ・[データラベル] → [外側末端]
B24: ・[凡例] → [なし](または凡例をクリックして delete キー)
B25: タイトルや「軸ラベル」の文字はクリックして書き換える
... B31: 凡例が非表示で、データラベルが表示されている

Sheet 問題2
B1: 問題2 折れ線グラフ
B2: 難易度 ★
B4: 月 | C4: 製品A(万円) | D4: 製品B(万円)
B5: 1月 | C5: 120 | D5: 80
B6: 2月 | C6: 115 | D6: 95
B7: 3月 | C7: 140 | D7: 100
B8: 4月 | C8: 155 | D8: 110
B9: 5月 | C9: 170 | D9: 105
B10: 6月 | C10: 190 | D10: 120
B11: 7月 | C11: 230 | D11: 130
B12: 8月 | C12: 250 | D12: 125
B13: 9月 | C13: 200 | D13: 140
B14: 10月 | C14: 175 | D14: 150
B15: 11月 | C15: 160 | D15: 165
B16: 12月 | C16: 210 | D16: 180
B19: 【問題】
B20: B4:D16 のデータから「マーカー付き折れ線グラフ」を作成しなさい。
B21: ・グラフタイトル:「製品別 月次売上推移」
B22: ・縦軸ラベル:「売上(万円)」
B23: ・凡例をグラフの下に表示
B24: ・縦軸の最小値を 50 に変更(変化を見やすくする)
B26: 【ヒント(操作手順)】
B27: B4:D16 を選択 → [挿入]タブ → 折れ線グラフのアイコン → [マーカー付き折れ線]
B28: 軸ラベル:[グラフのデザイン] → [グラフ要素を追加] → [軸ラベル] → [第1縦軸]
B29: 凡例:[グラフのデザイン] → [グラフ要素を追加] → [凡例] → [下]
B30: 縦軸の数字を右クリック → [軸の書式設定] → 右側の画面の[軸のオプション] →「境界値」の「最小値」に 50 と入力して return
B32: 【セルフチェック】できたら C列に ○ を入力
... B36: (考察)製品Aが最も売れた月は? → 8月

Sheet 問題3
B1: 問題3 円グラフ
B2: 難易度 ★
B4: 費目 | C4: 金額(千円) | D4: 構成比
B5: 人件費 | C5: 4500 | D5: =C5/SUM($C$5:$C$10) -> 0.5
B6: 家賃 | C6: 1800 | D6: =C6/SUM($C$5:$C$10) -> 0.2
B7: 広告宣伝費 | C7: 1200 | D7: =C7/SUM($C$5:$C$10) -> 0.13333333
B8: 水道光熱費 | C8: 600 | D8: =C8/SUM($C$5:$C$10) -> 0.066666667
B9: 通信費 | C9: 400 | D9: =C9/SUM($C$5:$C$10) -> 0.044444444
B10: その他 | C10: 500 | D10: =C10/SUM($C$5:$C$10) -> 0.055555556
B13: 【問題】
B14: B4:C10 のデータから「円グラフ」を作成しなさい。(構成比の列 D は使わない)
B15: ・グラフタイトル:「経費の構成比」
B16: ・データラベルに「分類名」と「パーセンテージ」を表示し、値は表示しない
B17: ・凡例は非表示
B18: (発展)最大の要素「人件費」を少し切り離して強調してみよう
B20: 【ヒント(操作手順)】
B21: B4:C10 を選択 → [挿入]タブ → 円グラフのアイコン → [円]
B22: [グラフのデザイン] → [グラフ要素を追加] → [データラベル] → [その他のデータラベルオプション]
B23: → 右側の画面「ラベルの内容」で 分類名・パーセンテージ にチェック、値 のチェックを外す
B24: 凡例:[グラフ要素を追加] → [凡例] → [なし]
B25: 切り離し:人件費の扇形だけをゆっくり2回クリックして選択 → 外側へドラッグ
... B31: ラベルの%とD列の構成比が一致している

Sheet 問題4
B1: 問題4 積み上げ縦棒グラフ
B2: 難易度 ★★
B4: 四半期 | C4: 食品 | D4: 日用品 | E4: 衣料 | F4: 家電
B5: 第1四半期 | C5: 320 | D5: 210 | E5: 150 | F5: 90
B6: 第2四半期 | C6: 350 | D6: 240 | E6: 170 | F6: 110
B7: 第3四半期 | C7: 300 | D7: 280 | E7: 200 | F7: 130
B8: 第4四半期 | C8: 410 | D8: 300 | E8: 220 | F8: 160
B11: 【問題】
B12: B4:F8 のデータから「積み上げ縦棒グラフ」を作成しなさい。(単位:百万円)
B13: ・横軸が四半期、積み上げの要素が部門(食品・日用品・衣料・家電)になるようにする
B14: ・グラフタイトル:「四半期別 部門売上(百万円)」
B15: ・棒の間隔(要素の間隔)を 60% にして棒を太くする
B16: (発展)同じデータで「100%積み上げ縦棒」も作り、構成比の変化を比べよう
B18: 【ヒント(操作手順)】
B19: B4:F8 を選択 → [挿入]タブ → 縦棒グラフのアイコン → [積み上げ縦棒]
B20: 横軸が部門になってしまったら:グラフを選択 → [グラフのデザイン]タブ → [行/列の切り替え]
B21: 棒を右クリック → [データ系列の書式設定] → 右側の画面[系列のオプション] →「要素の間隔」を 60%
B22: 100%積み上げ:グラフを選択 → [グラフのデザイン] → [グラフの種類の変更] → [100%積み上げ縦棒]
B24: 【セルフチェック】できたら C列に ○ を入力
... B28: (考察)合計売上が最も大きい四半期は? → 第4四半期

Sheet 問題5
B1: 問題5 横棒グラフ(並べ替え)
B2: 難易度 ★★
B4: 商品 | C4: 売上個数
B5: ボールペン | C5: 820
B6: ノート | C6: 1340
B7: 付箋 | C7: 560
B8: ファイル | C8: 970
B9: ハサミ | C9: 310
B10: のり | C10: 450
B11: 消しゴム | C11: 390
B12: マーカー | C12: 1120
B15: 【問題】
B16: B4:C12 のデータから、売上個数が多い商品ほど上に来る「集合横棒グラフ」を作成しなさい。
B17: ・グラフタイトル:「商品別 売上個数ランキング」
B18: ・凡例は非表示、データラベル(値)を表示
B19: ・一番上が「ノート」、一番下が「ハサミ」になっていれば正解
B21: 【ヒント(操作手順)】
B22: B4:C12 を選択 → [挿入]タブ → 縦棒グラフのアイコン → 横棒の中の[集合横棒]
B23: そのままだと表の上の行がグラフの下に来る(横棒の特徴)
B24: 方法①:B4:C12 を選択 → [データ]タブ → [並べ替え] → 列「売上個数」・順序「昇順」
B25: 方法②:データを『降順』に並べ替え → 縦軸(商品名)を右クリック → [軸の書式設定] →「軸を反転する」にチェック
B26: データラベル:[グラフのデザイン] → [グラフ要素を追加] → [データラベル] → [外側末端]
B28: 【セルフチェック】できたら C列に ○ を入力
... B30: 凡例が非表示でデータラベルがある

Sheet 問題6
B1: 問題6 複合グラフ(第2軸)
B2: 難易度 ★★★
B4: 年度 | C4: 売上高(百万円) | D4: 営業利益(百万円) | E4: 営業利益率
B5: 2020 | C5: 5200 | D5: 312 | E5: =D5/C5 -> 0.06
B6: 2021 | C6: 5800 | D6: 406 | E6: =D6/C6 -> 0.07
B7: 2022 | C7: 6100 | D7: 366 | E7: =D7/C7 -> 0.06
B8: 2023 | C8: 6900 | D8: 552 | E8: =D8/C8 -> 0.08
B9: 2024 | C9: 7400 | D9: 666 | E9: =D9/C9 -> 0.09
B10: 2025 | C10: 8200 | D10: 820 | E10: =D10/C10 -> 0.1
B12: 【問題】
B13: 売上高(C列)を「集合縦棒」、営業利益率(E列)を「マーカー付き折れ線」で表す複合グラフを作成しなさい。
B14: ・営業利益率は第2軸(右側の縦軸)に表示する
B15: ・グラフタイトル:「売上高と営業利益率の推移」
B16: ・左軸ラベル:「売上高(百万円)」、右軸ラベル:「営業利益率」
B17: ・営業利益(D列)はグラフに含めない
B18: ※ E列の営業利益率は数式です。まず式の中身を確認しよう
B20: 【ヒント(操作手順)】
B21: B4:C10 を選択 → ⌘(command)キーを押しながら E4:E10 を選択(離れた範囲の同時選択)
B22: [挿入]タブ → 縦棒グラフのアイコン → [集合縦棒](利益率の棒は小さすぎてほぼ見えない)
B23: 利益率の系列を選ぶ:[書式]タブ左端のプルダウンで 系列"営業利益率" を選択
B24: [グラフのデザイン] → [グラフの種類の変更] → [マーカー付き折れ線]
... B33: (考察)営業利益率が下がった年度は? → 2022年度

Sheet 問題7
B1: 問題7 散布図+近似曲線
B2: 難易度 ★★★
B4: 店舗 | C4: 広告費(万円) | D4: 売上(万円)
B5: 店舗01 | C5: 10 | D5: 180
B6: 店舗02 | C6: 15 | D6: 210
B7: 店舗03 | C7: 20 | D7: 260
B8: 店舗04 | C8: 25 | D8: 270
B9: 店舗05 | C9: 30 | D9: 320
B10: 店舗06 | C10: 35 | D10: 330
B11: 店舗07 | C11: 40 | D11: 390
B12: 店舗08 | C12: 45 | D12: 400
B13: 店舗09 | C13: 50 | D13: 450
B14: 店舗10 | C14: 55 | D14: 470
B15: 店舗11 | C15: 60 | D15: 500
B16: 店舗12 | C16: 65 | D16: 540
B18: 相関係数 | C18: =CORREL(C5:C16,D5:D16) -> 0.99687107
B19: 傾き | C19: =SLOPE(D5:D16,C5:C16) -> 6.4615385
B20: 切片 | C20: =INTERCEPT(D5:D16,C5:C16) -> 117.69231
B21: 【問題】
B22: 広告費(C列)を横軸、売上(D列)を縦軸にした「散布図」を作成しなさい。(店舗名 B列は使わない)
B23: ・グラフタイトル:「広告費と売上の関係」、横軸ラベル:「広告費(万円)」、縦軸ラベル:「売上(万円)」
B24: ・線形近似曲線を追加し、「数式」と「R-2乗値」をグラフに表示する
B25: ・グラフの数式の傾き・切片が、C19・C20 の関数の結果と一致することを確認する
B27: 【ヒント(操作手順)】
B28: C4:D16 を選択 → [挿入]タブ → 散布図のアイコン → [散布図](点だけのもの)
B29: [グラフのデザイン] → [グラフ要素を追加] → [近似曲線] → [その他の近似曲線オプション]
B30: → 右側の画面で「線形近似」を選び、下の「グラフに数式を表示する」「グラフに R-2 乗値を表示する」にチェック
B31: 軸ラベル:[グラフ要素を追加] → [軸ラベル] → [第1横軸] と [第1縦軸]
B32: 散布図では左の列が自動的に X(横軸)になる
B33: CORREL=相関係数(1に近いほど強い正の相関)、R-2乗値=相関係数の2乗
... B39: (考察)広告費70万円のときの予測売上は? → 約570万円

Sheet 解答1
B1: 問題1 集合縦棒グラフ【解答】
B2: 難易度 ★
B4: 支店 | C4: 売上(千円)
B5: 札幌 | C5: 4200
B6: 仙台 | C6: 3100
B7: 東京 | C7: 8600
B8: 名古屋 | C8: 5400
B9: 大阪 | C9: 7300
B10: 福岡 | C10: 3900
B11: 合計 | C11: =SUM(C5:C10) -> 32500

Sheet 解答2
B1: 問題2 折れ線グラフ【解答】
B2: 難易度 ★
B4: 月 | C4: 製品A(万円) | D4: 製品B(万円)
B5: 1月 | C5: 120 | D5: 80
B6: 2月 | C6: 115 | D6: 95
B7: 3月 | C7: 140 | D7: 100
B8: 4月 | C8: 155 | D8: 110
B9: 5月 | C9: 170 | D9: 105
B10: 6月 | C10: 190 | D10: 120
B11: 7月 | C11: 230 | D11: 130
B12: 8月 | C12: 250 | D12: 125
B13: 9月 | C13: 200 | D13: 140
B14: 10月 | C14: 175 | D14: 150
B15: 11月 | C15: 160 | D15: 165
B16: 12月 | C16: 210 | D16: 180

Sheet 解答3
B1: 問題3 円グラフ【解答】
B2: 難易度 ★
B4: 費目 | C4: 金額(千円) | D4: 構成比
B5: 人件費 | C5: 4500 | D5: =C5/SUM($C$5:$C$10) -> 0.5
B6: 家賃 | C6: 1800 | D6: =C6/SUM($C$5:$C$10) -> 0.2
B7: 広告宣伝費 | C7: 1200 | D7: =C7/SUM($C$5:$C$10) -> 0.13333333
B8: 水道光熱費 | C8: 600 | D8: =C8/SUM($C$5:$C$10) -> 0.066666667
B9: 通信費 | C9: 400 | D9: =C9/SUM($C$5:$C$10) -> 0.044444444
B10: その他 | C10: 500 | D10: =C10/SUM($C$5:$C$10) -> 0.055555556

Sheet 解答4
B1: 問題4 積み上げ縦棒グラフ【解答】
B2: 難易度 ★★
B4: 四半期 | C4: 食品 | D4: 日用品 | E4: 衣料 | F4: 家電
B5: 第1四半期 | C5: 320 | D5: 210 | E5: 150 | F5: 90
B6: 第2四半期 | C6: 350 | D6: 240 | E6: 170 | F6: 110
B7: 第3四半期 | C7: 300 | D7: 280 | E7: 200 | F7: 130
B8: 第4四半期 | C8: 410 | D8: 300 | E8: 220 | F8: 160

Sheet 解答5
B1: 問題5 横棒グラフ(並べ替え)【解答】
B2: 難易度 ★★
B4: 商品 | C4: 売上個数
B5: ハサミ | C5: 310
B6: 消しゴム | C6: 390
B7: のり | C7: 450
B8: 付箋 | C8: 560
B9: ボールペン | C9: 820
B10: ファイル | C10: 970
B11: マーカー | C11: 1120
B12: ノート | C12: 1340
B14: ※ データを「売上個数」の昇順に並べ替えてから作成(横棒は下から順に描かれるため、昇順にすると上が1位になる)

Sheet 解答6
B1: 問題6 複合グラフ(第2軸)【解答】
B2: 難易度 ★★★
B4: 年度 | C4: 売上高(百万円) | D4: 営業利益(百万円) | E4: 営業利益率
B5: 2020 | C5: 5200 | D5: 312 | E5: =D5/C5 -> 0.06
B6: 2021 | C6: 5800 | D6: 406 | E6: =D6/C6 -> 0.07
B7: 2022 | C7: 6100 | D7: 366 | E7: =D7/C7 -> 0.06
B8: 2023 | C8: 6900 | D8: 552 | E8: =D8/C8 -> 0.08
B9: 2024 | C9: 7400 | D9: 666 | E9: =D9/C9 -> 0.09
B10: 2025 | C10: 8200 | D10: 820 | E10: =D10/C10 -> 0.1

Sheet 解答7
B1: 問題7 散布図+近似曲線【解答】
B2: 難易度 ★★★
B4: 店舗 | C4: 広告費(万円) | D4: 売上(万円)
B5: 店舗01 | C5: 10 | D5: 180
B6: 店舗02 | C6: 15 | D6: 210
B7: 店舗03 | C7: 20 | D7: 260
B8: 店舗04 | C8: 25 | D8: 270
B9: 店舗05 | C9: 30 | D9: 320
B10: 店舗06 | C10: 35 | D10: 330
B11: 店舗07 | C11: 40 | D11: 390
B12: 店舗08 | C12: 45 | D12: 400
B13: 店舗09 | C13: 50 | D13: 450
B14: 店舗10 | C14: 55 | D14: 470
B15: 店舗11 | C15: 60 | D15: 500
B16: 店舗12 | C16: 65 | D16: 540
B18: 相関係数 | C18: =CORREL(C5:C16,D5:D16) -> 0.99687107
B19: 傾き | C19: =SLOPE(D5:D16,C5:C16) -> 6.4615385
B20: 切片 | C20: =INTERCEPT(D5:D16,C5:C16) -> 117.69231
