Workbook

Sheet 使い方
B2: 記帳設計シート(財務諸表の記帳方法の設計図)
B3: 会社の記帳ルールを、8つの領域・62項目で決めていくためのブックです。
B5: シートの構成
B6: 設計シート | C6: 62項目の設定を記入するメインのシート。選択肢がある項目は、セルを選ぶとリストから選べる
B7: 勘定科目表 | C7: 使う勘定科目の一覧のひな形。不要な科目は「使う」を×にし、自社の科目を追加する
B8: 決算整理チェック | C8: 決算整理事項ごとの仕訳の型と、担当・期限・完了を管理する
B9: 進捗 | C9: 領域ごとに、状態を「決定」にした項目の数を自動で集計する(数式なので記入不要)
B11: 記入のルール
B12: 黄色のセル | C12: 記入する欄。それ以外のセルは説明・数式なので、そのままにしておく
B13: 状態 | C13: 未着手 → 検討中 → 決定 の3つから選ぶ。「決定」にすると緑色になり、進捗に数えられる
B14: 記入例の列 | C14: 設計シートの「記入例」は、中小の卸売業を想定した一例。そのまま写さず、自社に合わせて決める
B15: 複数選ぶ項目 | C15: 選択肢が複数選べる項目(「複数可」と書いた項目)は、「・」で区切って入力する
B17: 設計の順番
B18: おすすめの順番 | C18: ① 前提条件 → ④ 会計方針 → ③ 勘定科目体系 → ② 帳簿組織 → ⑤ 日常取引の記帳ルール → ⑥ 月次・決算プロセス → ⑦ 財務諸表の表示ルール
B19: 理由 | C19: 会計方針を先に決めないと、必要な勘定科目が決まらない。例:売上原価対立法なら「商品」「売上原価」、三分法なら「仕入」「繰越商品」が必要
B20: ⑧ 統制・保存・税務 | C20: 全工程と並行して整える

Sheet 設計シート
A1: 記帳設計シート
A2: 会社名 | F2: 決定 | G2: =COUNTIF(H6:H75,"決定")&" / "&COUNTA(H6:H75)&" 項目" -> 0 / 62 項目
F3: 進捗率 | G3: =IFERROR(COUNTIF(H6:H75,"決定")/COUNTA(H6:H75),0) -> 0
A5: No | B5: 領域 | C5: 設定項目 | D5: 選択肢 | E5: 記入のヒント | F5: 自社の設定 | G5: 決めた理由・メモ | H5: 状態 | I5: 記入例 | J5: 仕訳の例
A6: ① 前提条件 ― すべての土台。ここが決まらないと他が決まらない
A7: 1-1 | B7: 前提条件 | C7: 適用する会計基準 | D7: 企業会計基準(日本基準) / 中小企業の会計に関する指針 / 中小企業の会計に関する基本要領 / IFRS(国際財務報告基準) | E7: 上場会社や会計監査人を置く会社は企業会計基準。中小企業は指針か要領を選ぶことが多い | H7: 未着手 | I7: 中小企業の会計に関する指針
A8: 1-2 | B8: 前提条件 | C8: 決算日(会計期間) | D8: (自由記入) | E8: 例:3月31日(4月1日〜翌3月31日) | H8: 未着手 | I8: 3月31日
A9: 1-3 | B9: 前提条件 | C9: 月次決算 | D9: 毎月行う / 四半期ごとに行う / 年1回の決算だけ | E9: 毎月行うと、試算表で業績を早く確認できる | H9: 未着手 | I9: 毎月行う
A10: 1-4 | B10: 前提条件 | C10: 記帳の単位 | D10: 会社全体で1本 / 本支店会計 / 部門別会計 | E10: 支店が独立して記帳するなら本支店会計。決算で本支店合併財務諸表を作る | H10: 未着手 | I10: 部門別会計
A11: 1-5 | B11: 前提条件 | C11: 消費税の経理方式 | D11: 税抜方式 / 税込方式 | E11: 税抜方式は消費税を仮払消費税・仮受消費税で分けて記録する。課税事業者は税抜方式が一般的 | H11: 未着手 | I11: 税抜方式 | J11: 【税抜方式】 商品1,000円(税100円)を掛けで仕入れた (借)仕入 1,000 ／ (貸)買掛金 1,100 (借)仮払消費税 100 決算:仮受消費税300・仮払消費税100を相殺 (借)仮受消費税 300 ／ (貸)仮払消費税 100 ／ (貸)未払消費税 200 【税込方式】 商品1,000円(税100円)を掛けで仕入れた (借)仕入 1,100 ／ (貸)買掛金 1,100 決算:納付額200を計上 (借)租税公課 200 ／ (貸)未払消費税 200
A12: 1-6 | B12: 前提条件 | C12: 消費税の計算方法 | D12: 本則課税(原則課税) / 簡易課税 / 免税事業者 | E12: 簡易課税は基準期間の課税売上高5,000万円以下で、届出をした場合に選べる | H12: 未着手 | I12: 本則課税(原則課税)
A13: 1-7 | B13: 前提条件 | C13: インボイス(適格請求書発行事業者) | D13: 登録している / 登録していない | E13: 仕入先が未登録の場合、仕入税額控除の経過措置の扱いも決めておく | H13: 未着手 | I13: 登録している
A14: 1-8 | B14: 前提条件 | C14: 通貨と端数処理 | D14: (自由記入) | E14: 例:円単位、1円未満は切り捨て | H14: 未着手 | I14: 円単位・1円未満切り捨て
A15: ② 帳簿組織 ― どの帳簿を置き、どうつなぐか
A16: 2-1 | B16: 帳簿組織 | C16: 仕訳の起票方法 | D16: 仕訳帳に直接記入 / 会計ソフトに直接入力 / 三伝票制(入金・出金・振替) / 五伝票制(+売上・仕入) | E16: 伝票制にすると、担当者ごとに分けて起票しやすい | H16: 未着手 | I16: 会計ソフトに直接入力 | J16: 【三伝票制(入金・出金・振替)】 入金伝票「売掛金 50,000」の意味 (借)現金 50,000 ／ (貸)売掛金 50,000 出金伝票「旅費交通費 3,000」の意味 (借)旅費交通費 3,000 ／ (貸)現金 3,000 【五伝票制(+売上・仕入)】 売上伝票「A社 80,000」の意味(すべて掛けとして起票) (借)売掛金 80,000 ／ (貸)売上 80,000
A17: 2-2 | B17: 帳簿組織 | C17: 一部現金取引の起票 | D17: 取引を分解して起票 / いったん全額掛けとして起票 | E17: 例:売上100,000のうち30,000を現金で受け取り、残りは掛け。伝票制を使うときに決める | H17: 未着手 | I17: いったん全額掛けとして起票 | J17: 【取引を分解して起票】 入金伝票 (借)現金 30,000 ／ (貸)売上 30,000 振替伝票 (借)売掛金 70,000 ／ (貸)売上 70,000 【いったん全額掛けとして起票】 振替伝票 (借)売掛金 100,000 ／ (貸)売上 100,000 入金伝票 (借)現金 30,000 ／ (貸)売掛金 30,000
A18: 2-3 | B18: 帳簿組織 | C18: 総勘定元帳への転記 | D18: 仕訳ごとに1件ずつ転記 / 仕訳日計表で毎日まとめて転記 / 仕訳週計表で毎週まとめて転記 | E18: 会計ソフトなら入力と同時に自動で転記される | H18: 未着手 | I18: 仕訳ごとに1件ずつ転記
A19: 2-4 | B19: 帳簿組織 | C19: 使う補助記入帳 | D19: (複数可)現金出納帳・当座預金出納帳・小口現金出納帳・売上帳・仕入帳・受取手形記入帳・支払手形記入帳 | E19: 取引の明細を日付順に記録する帳簿 | H19: 未着手 | I19: 現金出納帳・当座預金出納帳・売上帳・仕入帳
A20: 2-5 | B20: 帳簿組織 | C20: 使う補助元帳 | D20: (複数可)売掛金元帳(得意先元帳)・買掛金元帳(仕入先元帳)・商品有高帳・固定資産台帳 | E20: 勘定の内訳を、相手先別・品目別に記録する帳簿 | H20: 未着手 | I20: 売掛金元帳(得意先元帳)・買掛金元帳(仕入先元帳)・固定資産台帳
A21: 2-6 | B21: 帳簿組織 | C21: 使う会計ソフト・システム | D21: (自由記入) | E21: 例:クラウド会計ソフト、販売管理システムと連携 | H21: 未着手 | I21: クラウド会計ソフト(銀行明細を自動取込)
A22: ③ 勘定科目体系 ― 会社の“科目の辞書”を作る
A23: 3-1 | B23: 勘定科目体系 | C23: 科目コードのルール | D23: (自由記入) | E23: 例:4桁で、先頭1=資産、2=負債、3=純資産、4=収益、5〜=費用 | H23: 未着手 | I23: 4桁(1xxx資産・2xxx負債・3xxx純資産・4xxx収益・5xxx以降費用)
A24: 3-2 | B24: 勘定科目体系 | C24: 預金の補助科目 | D24: 口座ごとに設定する / 設定しない | E24: 口座ごとに分けると、銀行残高との照合がしやすい | H24: 未着手 | I24: 口座ごとに設定する
A25: 3-3 | B25: 勘定科目体系 | C25: 売掛金・買掛金の内訳管理 | D25: 取引先ごとに補助科目を設定 / 補助元帳だけで管理 / 管理しない | E25: 総勘定元帳の売掛金(統制勘定)と、取引先別の合計が一致するようにする | H25: 未着手 | I25: 取引先ごとに補助科目を設定
A26: 3-4 | B26: 勘定科目体系 | C26: 部門・プロジェクトの管理 | D26: 部門タグを使う / 部門とプロジェクトのタグを使う / 使わない | E26: 管理会計(部門別の損益)を見るかどうかで決める | H26: 未着手 | I26: 部門タグを使う
A27: 3-5 | B27: 勘定科目体系 | C27: 費用科目の細かさ | D27: (自由記入) | E27: 例:消耗品費と事務用品費を分けるか。分けすぎると入力ミスが増える | H27: 未着手 | I27: 少額の備品・文具はまとめて消耗品費
A28: 3-6 | B28: 勘定科目体系 | C28: 表示科目へのまとめ方 | D28: (自由記入) | E28: 帳簿の科目を財務諸表の表示科目にまとめるルール | H28: 未着手 | I28: 現金・当座預金・普通預金 → 現金及び預金
A29: ④ 会計方針 ― 財務諸表の数字そのものが変わる最重要部分
A30: 4-1 | B30: 会計方針 | C30: 収益を計上するタイミング | D30: 出荷基準 / 着荷基準 / 検収基準 | E30: 収益認識基準では、支配が顧客に移った時点で計上する。国内販売なら出荷基準も認められる場合がある | H30: 未着手 | I30: 出荷基準 | J30: 仕訳の形は同じで、計上する日が変わる (借)売掛金 150,000 ／ (貸)売上 150,000
A31: 4-2 | B31: 会計方針 | C31: 商品売買の記帳法 | D31: 三分法 / 売上原価対立法 / 分記法 | E31: 原価1,000円の商品を1,500円で掛け売りした場合で比べる | H31: 未着手 | I31: 三分法 | J31: 【三分法】 販売時 (借)売掛金 1,500 ／ (貸)売上 1,500 決算:期首商品200・期末商品300 (借)仕入 200 ／ (貸)繰越商品 200 (借)繰越商品 300 ／ (貸)仕入 300 【売上原価対立法】 販売時に原価も計上する (借)売掛金 1,500 ／ (貸)売上 1,500 (借)売上原価 1,000 ／ (貸)商品 1,000 【分記法】 販売時に利益を分けて計上する (借)売掛金 1,500 ／ (貸)商品 1,000 ／ (貸)商品売買益 500
A32: 4-3 | B32: 会計方針 | C32: 払出単価の計算方法 | D32: 先入先出法 / 移動平均法 / 総平均法 | E32: 商品有高帳の付け方と売上原価の金額が変わる | H32: 未着手 | I32: 移動平均法
A33: 4-4 | B33: 会計方針 | C33: 棚卸資産の簿価切下げ | D33: 洗替法 / 切放法 | E33: 正味売却価額が帳簿価額を下回ったら切り下げる。洗替法は翌期首に戻し入れる | H33: 未着手 | I33: 洗替法 | J33: 【洗替法】 決算:評価損20を計上 (借)商品評価損 20 ／ (貸)繰越商品 20 翌期首:戻し入れ (借)繰越商品 20 ／ (貸)商品評価損戻入益 20 【切放法】 決算:評価損20を計上(翌期は戻さない) (借)商品評価損 20 ／ (貸)繰越商品 20
A34: 4-5 | B34: 会計方針 | C34: 減価償却の方法 | D34: 定額法 / 定率法(200%定率法) / 生産高比例法 | E34: 例:取得原価1,000,000円・耐用年数5年・残存価額0の備品の1年目 | H34: 未着手 | I34: 定額法 | J34: 【定額法】 1,000,000 ÷ 5年 = 200,000 (借)減価償却費 200,000 ／ (貸)備品減価償却累計額 200,000 【定率法(200%定率法)】 償却率 1÷5年×200% = 0.400、1,000,000 × 0.400 = 400,000 (借)減価償却費 400,000 ／ (貸)備品減価償却累計額 400,000 【生産高比例法】 総見積生産量10,000個のうち当期2,500個 → 1,000,000 × 2,500/10,000 = 250,000 (借)減価償却費 250,000 ／ (貸)機械装置減価償却累計額 250,000
A35: 4-6 | B35: 会計方針 | C35: 減価償却の記帳方法 | D35: 間接法 / 直接法 | E35: 間接法なら、取得原価と累計額を両方残せる | H35: 未着手 | I35: 間接法 | J35: 【間接法】 (借)減価償却費 100 ／ (貸)備品減価償却累計額 100 【直接法】 (借)減価償却費 100 ／ (貸)備品 100
A36: 4-7 | B36: 会計方針 | C36: 固定資産に計上する基準 | D36: (自由記入) | E36: 例:取得価額10万円以上は資産に計上し、未満は消耗品費 | H36: 未着手 | I36: 取得価額10万円以上を資産計上
A37: 4-8 | B37: 会計方針 | C37: 貸倒引当金の繰入方法 | D37: 差額補充法 / 洗替法 | E37: 例:設定額300、決算前の引当金残高100 | H37: 未着手 | I37: 差額補充法 | J37: 【差額補充法】 不足する200だけ繰り入れる (借)貸倒引当金繰入 200 ／ (貸)貸倒引当金 200 【洗替法】 残高100を戻し入れ、300を改めて繰り入れる (借)貸倒引当金 100 ／ (貸)貸倒引当金戻入 100 (借)貸倒引当金繰入 300 ／ (貸)貸倒引当金 300
A38: 4-9 | B38: 会計方針 | C38: 貸倒見積高の算定 | D38: (自由記入) | E38: 一般債権は貸倒実績率法、貸倒懸念債権は財務内容評価法など、債権の区分ごとに決める | H38: 未着手 | I38: 一般債権:過去3年の貸倒実績率
A39: 4-10 | B39: 会計方針 | C39: その他に計上する引当金 | D39: (複数可)賞与引当金・退職給付引当金・修繕引当金・製品保証引当金 | E39: 将来の費用で、発生の可能性が高く金額を見積もれるものを計上する | H39: 未着手 | I39: 賞与引当金
A40: 4-11 | B40: 会計方針 | C40: その他有価証券の評価差額 | D40: 全部純資産直入法 / 部分純資産直入法 | E40: 違いが出るのは評価差損のとき。例:取得原価1,000、期末時価900 | H40: 未着手 | I40: 全部純資産直入法 | J40: 【全部純資産直入法】 評価差損も純資産に直接計上(税効果は省略) (借)その他有価証券評価差額金 100 ／ (貸)その他有価証券 100 【部分純資産直入法】 評価差損は当期の損失に計上(税効果は省略) (借)投資有価証券評価損 100 ／ (貸)その他有価証券 100
A41: 4-12 | B41: 会計方針 | C41: 外貨建取引の換算レート | D41: (自由記入) | E41: 取引日の直物レートが原則。前月末レートなど合理的なレートを使うこともある | H41: 未着手 | I41: 取引日の直物レート(TTM)
A42: 4-13 | B42: 会計方針 | C42: 税効果会計 | D42: 適用する / 適用しない | E42: 会計上の利益と税務上の所得のズレのうち、一時差異を調整する | H42: 未着手 | I42: 適用する | J42: 【適用する】 減価償却の損金算入限度超過額1,000、実効税率30% (借)繰延税金資産 300 ／ (貸)法人税等調整額 300
A43: ⑤ 日常取引の記帳ルール ― 取引ごとに“仕訳の型”を決める
A44: 5-1 | B44: 日常取引の記帳ルール | C44: 小口現金 | D44: 定額資金前渡法(インプレスト・システム) / 随時補給法 / 小口現金を置かない | E44: 定額資金前渡法は、使った分だけを補給して毎回同じ額に戻す | H44: 未着手 | I44: 定額資金前渡法(インプレスト・システム) | J44: 【定額資金前渡法(インプレスト・システム)】 30,000を前渡し (借)小口現金 30,000 ／ (貸)当座預金 30,000 使った分の報告を受け、すぐ補給した (借)旅費交通費 8,000 ／ (貸)当座預金 13,000 (借)消耗品費 5,000
A45: 5-2 | B45: 日常取引の記帳ルール | C45: 現金過不足の処理 | D45: (自由記入) | E45: 原因が分かるまでは現金過不足で処理し、決算まで分からなければ雑損・雑益へ | H45: 未着手 | I45: 原因不明分は決算で雑損・雑益に振替 | J45: 帳簿より現金が500少なかった (借)現金過不足 500 ／ (貸)現金 500 決算:原因が分からなかった (借)雑損 500 ／ (貸)現金過不足 500
A46: 5-3 | B46: 日常取引の記帳ルール | C46: 受け取る・支払う手段 | D46: (複数可)約束手形・電子記録債権・債務・クレジット払い・銀行振込のみ | E46: 使う手段ごとに勘定科目を用意する | H46: 未着手 | I46: 電子記録債権・債務・銀行振込のみ
A47: 5-4 | B47: 日常取引の記帳ルール | C47: クレジット売上の手数料 | D47: 販売時に計上 / 入金時に計上 | E47: 例:売上100,000、手数料4% | H47: 未着手 | I47: 販売時に計上 | J47: 【販売時に計上】 (借)クレジット売掛金 96,000 ／ (貸)売上 100,000 (借)支払手数料 4,000 【入金時に計上】 販売時 (借)クレジット売掛金 100,000 ／ (貸)売上 100,000 入金時 (借)普通預金 96,000 ／ (貸)クレジット売掛金 100,000 (借)支払手数料 4,000
A48: 5-5 | B48: 日常取引の記帳ルール | C48: 給与の預り金 | D48: 内容ごとに分ける / 預り金1つにまとめる | E48: 源泉所得税・住民税・社会保険料を分けると、納付額の確認がしやすい | H48: 未着手 | I48: 内容ごとに分ける | J48: 【内容ごとに分ける】 給料300,000を普通預金から支払った (借)給料 300,000 ／ (貸)所得税預り金 20,000 ／ (貸)社会保険料預り金 40,000 ／ (貸)普通預金 240,000 【預り金1つにまとめる】 給料300,000を普通預金から支払った (借)給料 300,000 ／ (貸)預り金 60,000 ／ (貸)普通預金 240,000
A49: 5-6 | B49: 日常取引の記帳ルール | C49: 経過勘定(前払・未払など)の計上 | D49: 毎月計上する / 決算時だけ計上する | E49: 月次決算をするなら毎月計上する | H49: 未着手 | I49: 毎月計上する
A50: 5-7 | B50: 日常取引の記帳ルール | C50: 期首の再振替仕訳 | D50: 行う / 行わない | E50: 経過勘定を期首に元の費用・収益の勘定へ戻す | H50: 未着手 | I50: 行う | J50: 【行う】 決算:家賃10,000が未払い (借)支払家賃 10,000 ／ (貸)未払家賃 10,000 翌期首:再振替 (借)未払家賃 10,000 ／ (貸)支払家賃 10,000
A51: 5-8 | B51: 日常取引の記帳ルール | C51: 証憑と承認の流れ | D51: (自由記入) | E51: どの書類を根拠に、誰が起票して誰が承認するか | H51: 未着手 | I51: 請求書を経理が起票 → 課長が承認 → 月末に支払
A52: 5-9 | B52: 日常取引の記帳ルール | C52: 仮払金・仮受金の精算期限 | D52: (自由記入) | E52: 長く残ると内容が分からなくなるので期限を決める | H52: 未着手 | I52: 発生した月の月末まで
A53: ⑥ 月次・決算プロセス ― 締めの手順とスケジュール
A54: 6-1 | B54: 月次・決算プロセス | C54: 売上・仕入の締め日 | D54: (自由記入) | E54: 例:末日締め、20日締め | H54: 未着手 | I54: 末日締め
A55: 6-2 | B55: 月次・決算プロセス | C55: 月次決算の完了期限 | D55: (自由記入) | E55: 例:翌月10営業日まで | H55: 未着手 | I55: 翌月10営業日まで
A56: 6-3 | B56: 月次・決算プロセス | C56: 作る試算表 | D56: 合計残高試算表 / 残高試算表 / 合計試算表 | E56: 合計残高試算表なら、取引の量と残高を両方確認できる | H56: 未着手 | I56: 合計残高試算表
A57: 6-4 | B57: 月次・決算プロセス | C57: 実地棚卸 | D57: 年1回(決算時) / 毎月 / 循環棚卸(場所ごとに順番に) | E57: 帳簿の数量と実際の数量の差は棚卸減耗損になる | H57: 未着手 | I57: 年1回(決算時) | J57: 帳簿数量100個・実地数量95個・原価@10 (借)棚卸減耗損 50 ／ (貸)繰越商品 50
A58: 6-5 | B58: 月次・決算プロセス | C58: 決算整理事項 | D58: (複数可)売上原価の計算・減価償却・貸倒引当金・経過勘定・有価証券の評価・外貨建項目の換算・その他の引当金・法人税等・消費税の整理 | E58: 毎回のチェックリストにする | H58: 未着手 | I58: 売上原価の計算・減価償却・貸倒引当金・経過勘定・法人税等・消費税の整理 | J58: 法人税等の計上:年税額500,000、中間納付200,000 (借)法人税、住民税及び事業税 500,000 ／ (貸)仮払法人税等 200,000 ／ (貸)未払法人税等 300,000
A59: 6-6 | B59: 月次・決算プロセス | C59: 精算表 | D59: 8桁精算表を作る / 10桁精算表を作る / 作らない | E59: 10桁は8桁に修正後試算表の欄を加えたもの | H59: 未着手 | I59: 作らない
A60: 6-7 | B60: 月次・決算プロセス | C60: 帳簿の締切方法 | D60: 英米式決算法 / 大陸式決算法 | E60: 英米式は資産・負債・純資産を繰越記入で締め切る。大陸式は残高勘定に振り替える | H60: 未着手 | I60: 英米式決算法 | J60: 【英米式決算法】 資産・負債・純資産の勘定には仕訳をせず、元帳に「次期繰越」と直接書いて締め切る 収益・費用は損益勘定に振り替える (借)売上 1,500 ／ (貸)損益 1,500 【大陸式決算法】 資産・負債・純資産も、仕訳で残高勘定に振り替える (借)残高 50,000 ／ (貸)現金 50,000 (借)買掛金 20,000 ／ (貸)残高 20,000
A61: ⑦ 財務諸表の表示ルール ― 作った数字をどう見せるか
A62: 7-1 | B62: 財務諸表の表示ルール | C62: 流動・固定の区分 | D62: (自由記入) | E62: まず正常営業循環基準で判定し、それ以外は1年基準で分ける | H62: 未着手 | I62: 正常営業循環基準 → 1年基準
A63: 7-2 | B63: 財務諸表の表示ルール | C63: 貸借対照表の配列 | D63: 流動性配列法 / 固定性配列法 | E63: 一般の会社は流動性配列法。電力会社などは固定性配列法 | H63: 未着手 | I63: 流動性配列法
A64: 7-3 | B64: 財務諸表の表示ルール | C64: 財務諸表の様式 | D64: 報告式 / 勘定式 / 損益計算書は報告式・貸借対照表は勘定式 | E64: 報告式は上から下へ並べる様式。勘定式は左右に並べる様式 | H64: 未着手 | I64: 損益計算書は報告式・貸借対照表は勘定式
A65: 7-4 | B65: 財務諸表の表示ルール | C65: 損益計算書の区分 | D65: (自由記入) | E65: 売上総利益 → 営業利益 → 経常利益 → 税引前当期純利益 → 当期純利益 | H65: 未着手 | I65: 区分損益計算(5段階の利益)
A66: 7-5 | B66: 財務諸表の表示ルール | C66: キャッシュ・フロー計算書 | D66: 作らない / 作る(営業CFは間接法) / 作る(営業CFは直接法) | E66: 上場会社などは作成が必要。間接法は税引前当期純利益から調整する | H66: 未着手 | I66: 作らない
A67: 7-6 | B67: 財務諸表の表示ルール | C67: 株主資本等変動計算書・注記 | D67: (自由記入) | E67: 会社計算規則・財務諸表等規則のどちらに従うか | H67: 未着手 | I67: 会社計算規則に従って作成
A68: 7-7 | B68: 財務諸表の表示ルール | C68: 金額の表示単位 | D68: 円単位 / 千円単位 / 百万円単位 | E68: 単位未満の端数の処理(切り捨てなど)も決める | H68: 未着手 | I68: 千円単位
A69: ⑧ 統制・保存・税務 ― 間違い・不正を防ぎ、記録を守る
A70: 8-1 | B70: 統制・保存・税務 | C70: 職務分掌 | D70: (自由記入) | E70: 起票・承認・支払を同じ人にさせない | H70: 未着手 | I70: 起票:担当者/承認:経理課長/支払:財務担当
A71: 8-2 | B71: 統制・保存・税務 | C71: 帳簿書類の保存期間 | D71: (自由記入) | E71: 会社法では会計帳簿は10年。法人税法では原則7年(欠損金が出た事業年度は10年) | H71: 未着手 | I71: 帳簿は10年、その他の税務書類は7年以上
A72: 8-3 | B72: 統制・保存・税務 | C72: 電子取引データの保存 | D72: 会計ソフト・クラウドに保存 / 社内サーバーに検索できる形で保存 / 事務処理規程を作って保存 | E72: 電子帳簿保存法により、メールやPDFで受け取った請求書は電子のまま保存する | H72: 未着手 | I72: 会計ソフト・クラウドに保存
A73: 8-4 | B73: 統制・保存・税務 | C73: 紙の書類のスキャナ保存 | D73: 使う / 使わない | E73: 使う場合は、読み取りの期限や解像度などの要件を満たす | H73: 未着手 | I73: 使わない
A74: 8-5 | B74: 統制・保存・税務 | C74: 申告調整の管理 | D74: (自由記入) | E74: 会計上の利益と課税所得の差(加算・減算)を一覧で管理する | H74: 未着手 | I74: 加算・減算項目を別表四の項目ごとに一覧管理
A75: 8-6 | B75: 統制・保存・税務 | C75: 決算の承認 | D75: (自由記入) | E75: 誰の承認で財務諸表を確定させるか | H75: 未着手 | I75: 取締役会で承認 → 定時株主総会で承認(または報告)

Sheet 勘定科目表
A1: 勘定科目表(ひな形)
A2: 黄色の「使う」を ○/× で選ぶ。自社で使う科目は空いている行に追加する。コードは「1xxx資産・2xxx負債・3xxx純資産・4xxx収益・5xxx以降費用」の例
G3: =COUNTIF(G5:G87,"○")&" 科目を使用" -> 68 科目を使用
A4: コード | B4: 勘定科目 | C4: 5要素 | D4: 表示区分 | E4: 財務諸表の表示科目 | F4: 補助科目(例) | G4: 使う | H4: メモ
A5: 1110 | B5: 現金 | C5: 資産 | D5: 流動資産 | E5: 現金及び預金 | G5: ○
A6: 1120 | B6: 小口現金 | C6: 資産 | D6: 流動資産 | E6: 現金及び預金 | G6: ○
A7: 1130 | B7: 当座預金 | C7: 資産 | D7: 流動資産 | E7: 現金及び預金 | F7: 口座ごと | G7: ○
A8: 1140 | B8: 普通預金 | C8: 資産 | D8: 流動資産 | E8: 現金及び預金 | F8: 口座ごと | G8: ○
A9: 1210 | B9: 受取手形 | C9: 資産 | D9: 流動資産 | E9: 受取手形 | F9: 取引先ごと | G9: ○
A10: 1220 | B10: 電子記録債権 | C10: 資産 | D10: 流動資産 | E10: 電子記録債権 | F10: 取引先ごと | G10: ○
A11: 1230 | B11: 売掛金 | C11: 資産 | D11: 流動資産 | E11: 売掛金 | F11: 取引先ごと | G11: ○
A12: 1240 | B12: クレジット売掛金 | C12: 資産 | D12: 流動資産 | E12: 売掛金 | F12: カード会社ごと | G12: ○
A13: 1250 | B13: 貸倒引当金 | C13: 資産(評価勘定) | D13: 流動資産 | E13: 貸倒引当金(控除) | G13: ○
A14: 1310 | B14: 有価証券 | C14: 資産 | D14: 流動資産 | E14: 有価証券 | F14: 銘柄ごと | G14: ○
A15: 1410 | B15: 商品(繰越商品) | C15: 資産 | D15: 流動資産 | E15: 商品 | G15: ○
A16: 1510 | B16: 前払費用 | C16: 資産 | D16: 流動資産 | E16: 前払費用 | G16: ○
A17: 1520 | B17: 未収収益 | C17: 資産 | D17: 流動資産 | E17: 未収収益 | G17: ○
A18: 1530 | B18: 仮払金 | C18: 資産 | D18: 流動資産 | E18: その他 | G18: ○
A19: 1540 | B19: 仮払消費税 | C19: 資産 | D19: 流動資産 | E19: (決算で相殺) | G19: ○
A20: 1550 | B20: 仮払法人税等 | C20: 資産 | D20: 流動資産 | E20: (決算で精算) | G20: ○
A21: 1610 | B21: 建物 | C21: 資産 | D21: 有形固定資産 | E21: 建物 | G21: ○
A22: 1611 | B22: 建物減価償却累計額 | C22: 資産(評価勘定) | D22: 有形固定資産 | E22: 減価償却累計額(控除) | G22: ○
A23: 1620 | B23: 備品 | C23: 資産 | D23: 有形固定資産 | E23: 工具、器具及び備品 | G23: ○
A24: 1621 | B24: 備品減価償却累計額 | C24: 資産(評価勘定) | D24: 有形固定資産 | E24: 減価償却累計額(控除) | G24: ○
A25: 1630 | B25: 車両運搬具 | C25: 資産 | D25: 有形固定資産 | E25: 車両運搬具 | G25: ○
A26: 1640 | B26: 土地 | C26: 資産 | D26: 有形固定資産 | E26: 土地 | G26: ○
A27: 1710 | B27: ソフトウェア | C27: 資産 | D27: 無形固定資産 | E27: ソフトウェア | G27: ○
A28: 1810 | B28: 投資有価証券 | C28: 資産 | D28: 投資その他の資産 | E28: 投資有価証券 | F28: 銘柄ごと | G28: ○
A29: 1820 | B29: 繰延税金資産 | C29: 資産 | D29: 投資その他の資産 | E29: 繰延税金資産 | G29: ○
A30: 2110 | B30: 支払手形 | C30: 負債 | D30: 流動負債 | E30: 支払手形 | F30: 取引先ごと | G30: ○
A31: 2120 | B31: 電子記録債務 | C31: 負債 | D31: 流動負債 | E31: 電子記録債務 | F31: 取引先ごと | G31: ○
A32: 2130 | B32: 買掛金 | C32: 負債 | D32: 流動負債 | E32: 買掛金 | F32: 取引先ごと | G32: ○
A33: 2140 | B33: 短期借入金 | C33: 負債 | D33: 流動負債 | E33: 短期借入金 | F33: 借入先ごと | G33: ○
A34: 2150 | B34: 未払金 | C34: 負債 | D34: 流動負債 | E34: 未払金 | G34: ○
A35: 2160 | B35: 未払費用 | C35: 負債 | D35: 流動負債 | E35: 未払費用 | G35: ○
A36: 2170 | B36: 未払法人税等 | C36: 負債 | D36: 流動負債 | E36: 未払法人税等 | G36: ○
A37: 2180 | B37: 未払消費税 | C37: 負債 | D37: 流動負債 | E37: 未払消費税等 | G37: ○
A38: 2190 | B38: 仮受消費税 | C38: 負債 | D38: 流動負債 | E38: (決算で相殺) | G38: ○
A39: 2210 | B39: 前受金 | C39: 負債 | D39: 流動負債 | E39: 前受金 | G39: ○
A40: 2220 | B40: 預り金 | C40: 負債 | D40: 流動負債 | E40: 預り金 | F40: 所得税・住民税・社会保険料 | G40: ○
A41: 2230 | B41: 賞与引当金 | C41: 負債 | D41: 流動負債 | E41: 賞与引当金 | G41: ○
A42: 2310 | B42: 長期借入金 | C42: 負債 | D42: 固定負債 | E42: 長期借入金 | F42: 借入先ごと | G42: ○
A43: 2320 | B43: 退職給付引当金 | C43: 負債 | D43: 固定負債 | E43: 退職給付引当金 | G43: ○
A44: 3110 | B44: 資本金 | C44: 純資産 | D44: 株主資本 | E44: 資本金 | G44: ○
A45: 3210 | B45: 資本準備金 | C45: 純資産 | D45: 株主資本 | E45: 資本準備金 | G45: ○
A46: 3310 | B46: 利益準備金 | C46: 純資産 | D46: 株主資本 | E46: 利益準備金 | G46: ○
A47: 3320 | B47: 繰越利益剰余金 | C47: 純資産 | D47: 株主資本 | E47: 繰越利益剰余金 | G47: ○
A48: 3410 | B48: その他有価証券評価差額金 | C48: 純資産 | D48: 評価・換算差額等 | E48: その他有価証券評価差額金 | G48: ○
A49: 4110 | B49: 売上 | C49: 収益 | D49: 売上高 | E49: 売上高 | F49: 部門ごと | G49: ○
A50: 4210 | B50: 受取利息 | C50: 収益 | D50: 営業外収益 | E50: 受取利息 | G50: ○
A51: 4220 | B51: 受取配当金 | C51: 収益 | D51: 営業外収益 | E51: 受取配当金 | G51: ○
A52: 4230 | B52: 雑益 | C52: 収益 | D52: 営業外収益 | E52: 雑収入 | G52: ○
A53: 4310 | B53: 固定資産売却益 | C53: 収益 | D53: 特別利益 | E53: 固定資産売却益 | G53: ○
A54: 5110 | B54: 仕入(売上原価) | C54: 費用 | D54: 売上原価 | E54: 売上原価 | G54: ○
A55: 5120 | B55: 棚卸減耗損 | C55: 費用 | D55: 売上原価または販管費 | E55: 棚卸減耗損 | G55: ○
A56: 5130 | B56: 商品評価損 | C56: 費用 | D56: 売上原価 | E56: 売上原価 | G56: ○
A57: 6110 | B57: 給料 | C57: 費用 | D57: 販売費及び一般管理費 | E57: 給料手当 | F57: 部門ごと | G57: ○
A58: 6120 | B58: 法定福利費 | C58: 費用 | D58: 販売費及び一般管理費 | E58: 法定福利費 | G58: ○
A59: 6130 | B59: 旅費交通費 | C59: 費用 | D59: 販売費及び一般管理費 | E59: 旅費交通費 | G59: ○
A60: 6140 | B60: 通信費 | C60: 費用 | D60: 販売費及び一般管理費 | E60: 通信費 | G60: ○
A61: 6150 | B61: 消耗品費 | C61: 費用 | D61: 販売費及び一般管理費 | E61: 消耗品費 | G61: ○
A62: 6160 | B62: 支払家賃 | C62: 費用 | D62: 販売費及び一般管理費 | E62: 地代家賃 | G62: ○
A63: 6170 | B63: 支払手数料 | C63: 費用 | D63: 販売費及び一般管理費 | E63: 支払手数料 | G63: ○
A64: 6180 | B64: 租税公課 | C64: 費用 | D64: 販売費及び一般管理費 | E64: 租税公課 | G64: ○
A65: 6190 | B65: 減価償却費 | C65: 費用 | D65: 販売費及び一般管理費 | E65: 減価償却費 | G65: ○
A66: 6200 | B66: 貸倒引当金繰入 | C66: 費用 | D66: 販売費及び一般管理費 | E66: 貸倒引当金繰入額 | G66: ○
A67: 6210 | B67: 賞与引当金繰入 | C67: 費用 | D67: 販売費及び一般管理費 | E67: 賞与引当金繰入額 | G67: ○
A68: 7110 | B68: 支払利息 | C68: 費用 | D68: 営業外費用 | E68: 支払利息 | G68: ○
A69: 7120 | B69: 雑損 | C69: 費用 | D69: 営業外費用 | E69: 雑損失 | G69: ○
... A72: 8120 | B72: 法人税等調整額 | C72: 費用 | D72: 税金等 | E72: 法人税等調整額 | G72: ○

Sheet 決算整理チェック
A1: 決算整理チェックリスト
A2: 毎回の決算で使う。黄色の欄(担当・期限・完了・メモ)を記入する。仕訳の金額は例 | G2: =COUNTIF(G5:G17,"済")&" / "&COUNTA(B5:B17)&" 完了" -> 0 / 13 完了
A4: No | B4: 決算整理事項 | C4: 仕訳の型(例) | D4: 根拠資料 | E4: 担当 | F4: 期限 | G4: 完了 | H4: メモ
A5: 1 | B5: 売上原価の計算(三分法) | C5: (借)仕入 200 ／(貸)繰越商品 200 (借)繰越商品 300 ／(貸)仕入 300 | D5: 商品有高帳・棚卸表 | G5: 未
A6: 2 | B6: 棚卸減耗損・商品評価損 | C6: (借)棚卸減耗損 50 ／(貸)繰越商品 50 (借)商品評価損 20 ／(貸)繰越商品 20 | D6: 実地棚卸表 | G6: 未
A7: 3 | B7: 減価償却 | C7: (借)減価償却費 200,000 ／(貸)備品減価償却累計額 200,000 | D7: 固定資産台帳 | G7: 未
A8: 4 | B8: 貸倒引当金(差額補充法) | C8: (借)貸倒引当金繰入 200 ／(貸)貸倒引当金 200 | D8: 売掛金元帳・貸倒実績率 | G8: 未
A9: 5 | B9: 経過勘定(前払・未払・未収・前受) | C9: (借)支払家賃 10,000 ／(貸)未払家賃 10,000 | D9: 契約書 | G9: 未
A10: 6 | B10: 有価証券の評価 | C10: (借)その他有価証券 100 ／(貸)その他有価証券評価差額金 100 | D10: 時価の資料 | G10: 未
A11: 7 | B11: 外貨建項目の換算 | C11: (借)売掛金 1,000 ／(貸)為替差損益 1,000 | D11: 決算日レート | G11: 未
A12: 8 | B12: 賞与・退職給付などの引当金 | C12: (借)賞与引当金繰入 500,000 ／(貸)賞与引当金 500,000 | D12: 支給見込額 | G12: 未
A13: 9 | B13: 現金過不足の整理 | C13: (借)雑損 500 ／(貸)現金過不足 500 | D13: 現金出納帳 | G13: 未
A14: 10 | B14: 消費税の整理(税抜方式) | C14: (借)仮受消費税 300 ／(貸)仮払消費税 100 ／(貸)未払消費税 200 | D14: 消費税の計算書 | G14: 未
A15: 11 | B15: 法人税等 | C15: (借)法人税、住民税及び事業税 500,000 ／(貸)仮払法人税等 200,000 ／(貸)未払法人税等 300,000 | D15: 税額計算書 | G15: 未
A16: 12 | B16: 税効果会計 | C16: (借)繰延税金資産 300 ／(貸)法人税等調整額 300 | D16: 一時差異の一覧 | G16: 未
A17: 13 | B17: 帳簿の締切・繰越 | C17: 収益・費用を損益勘定へ、当期純利益を繰越利益剰余金へ振替 | D17: 総勘定元帳 | G17: 未

Sheet 進捗
A1: 領域ごとの進捗(自動集計)
A2: 設計シートの「状態」から自動で計算する。記入は不要
A4: 領域 | B4: 項目数 | C4: 決定 | D4: 検討中 | E4: 未着手 | F4: 進捗率
A5: ① 前提条件 | B5: =COUNTIF(設計シート!$B$6:$B$75,"前提条件") -> 8 | C5: =COUNTIFS(設計シート!$B$6:$B$75,"前提条件",設計シート!$H$6:$H$75,"決定") -> 0 | D5: =COUNTIFS(設計シート!$B$6:$B$75,"前提条件",設計シート!$H$6:$H$75,"検討中") -> 0 | E5: =COUNTIFS(設計シート!$B$6:$B$75,"前提条件",設計シート!$H$6:$H$75,"未着手") -> 8 | F5: =IFERROR(C5/B5,0) -> 0
A6: ② 帳簿組織 | B6: =COUNTIF(設計シート!$B$6:$B$75,"帳簿組織") -> 6 | C6: =COUNTIFS(設計シート!$B$6:$B$75,"帳簿組織",設計シート!$H$6:$H$75,"決定") -> 0 | D6: =COUNTIFS(設計シート!$B$6:$B$75,"帳簿組織",設計シート!$H$6:$H$75,"検討中") -> 0 | E6: =COUNTIFS(設計シート!$B$6:$B$75,"帳簿組織",設計シート!$H$6:$H$75,"未着手") -> 6 | F6: =IFERROR(C6/B6,0) -> 0
A7: ③ 勘定科目体系 | B7: =COUNTIF(設計シート!$B$6:$B$75,"勘定科目体系") -> 6 | C7: =COUNTIFS(設計シート!$B$6:$B$75,"勘定科目体系",設計シート!$H$6:$H$75,"決定") -> 0 | D7: =COUNTIFS(設計シート!$B$6:$B$75,"勘定科目体系",設計シート!$H$6:$H$75,"検討中") -> 0 | E7: =COUNTIFS(設計シート!$B$6:$B$75,"勘定科目体系",設計シート!$H$6:$H$75,"未着手") -> 6 | F7: =IFERROR(C7/B7,0) -> 0
A8: ④ 会計方針 | B8: =COUNTIF(設計シート!$B$6:$B$75,"会計方針") -> 13 | C8: =COUNTIFS(設計シート!$B$6:$B$75,"会計方針",設計シート!$H$6:$H$75,"決定") -> 0 | D8: =COUNTIFS(設計シート!$B$6:$B$75,"会計方針",設計シート!$H$6:$H$75,"検討中") -> 0 | E8: =COUNTIFS(設計シート!$B$6:$B$75,"会計方針",設計シート!$H$6:$H$75,"未着手") -> 13 | F8: =IFERROR(C8/B8,0) -> 0
A9: ⑤ 日常取引の記帳ルール | B9: =COUNTIF(設計シート!$B$6:$B$75,"日常取引の記帳ルール") -> 9 | C9: =COUNTIFS(設計シート!$B$6:$B$75,"日常取引の記帳ルール",設計シート!$H$6:$H$75,"決定") -> 0 | D9: =COUNTIFS(設計シート!$B$6:$B$75,"日常取引の記帳ルール",設計シート!$H$6:$H$75,"検討中") -> 0 | E9: =COUNTIFS(設計シート!$B$6:$B$75,"日常取引の記帳ルール",設計シート!$H$6:$H$75,"未着手") -> 9 | F9: =IFERROR(C9/B9,0) -> 0
A10: ⑥ 月次・決算プロセス | B10: =COUNTIF(設計シート!$B$6:$B$75,"月次・決算プロセス") -> 7 | C10: =COUNTIFS(設計シート!$B$6:$B$75,"月次・決算プロセス",設計シート!$H$6:$H$75,"決定") -> 0 | D10: =COUNTIFS(設計シート!$B$6:$B$75,"月次・決算プロセス",設計シート!$H$6:$H$75,"検討中") -> 0 | E10: =COUNTIFS(設計シート!$B$6:$B$75,"月次・決算プロセス",設計シート!$H$6:$H$75,"未着手") -> 7 | F10: =IFERROR(C10/B10,0) -> 0
A11: ⑦ 財務諸表の表示ルール | B11: =COUNTIF(設計シート!$B$6:$B$75,"財務諸表の表示ルール") -> 7 | C11: =COUNTIFS(設計シート!$B$6:$B$75,"財務諸表の表示ルール",設計シート!$H$6:$H$75,"決定") -> 0 | D11: =COUNTIFS(設計シート!$B$6:$B$75,"財務諸表の表示ルール",設計シート!$H$6:$H$75,"検討中") -> 0 | E11: =COUNTIFS(設計シート!$B$6:$B$75,"財務諸表の表示ルール",設計シート!$H$6:$H$75,"未着手") -> 7 | F11: =IFERROR(C11/B11,0) -> 0
A12: ⑧ 統制・保存・税務 | B12: =COUNTIF(設計シート!$B$6:$B$75,"統制・保存・税務") -> 6 | C12: =COUNTIFS(設計シート!$B$6:$B$75,"統制・保存・税務",設計シート!$H$6:$H$75,"決定") -> 0 | D12: =COUNTIFS(設計シート!$B$6:$B$75,"統制・保存・税務",設計シート!$H$6:$H$75,"検討中") -> 0 | E12: =COUNTIFS(設計シート!$B$6:$B$75,"統制・保存・税務",設計シート!$H$6:$H$75,"未着手") -> 6 | F12: =IFERROR(C12/B12,0) -> 0
A13: 合計 | B13: =SUM(B5:B12) -> 62 | C13: =SUM(C5:C12) -> 0 | D13: =SUM(D5:D12) -> 0 | E13: =SUM(E5:E12) -> 62 | F13: =IFERROR(C13/B13,0) -> 0
